borco_shiboken_example/__init__.py
borco_shiboken_example/borco_shiboken_example.pyd
borco_shiboken_example/core_lib.dll
borco_shiboken_example-0.0.7.dist-info/METADATA
borco_shiboken_example-0.0.7.dist-info/WHEEL
borco_shiboken_example-0.0.7.dist-info/licenses/LICENSE.md
borco_shiboken_example-0.0.7.dist-info/RECORD
